vgrid_jupyter/__init__.py
vgrid_jupyter/_frontend.py
vgrid_jupyter/_version.py
vgrid_jupyter/vgrid_widget.py
vgrid_jupyter/labextension/vgrid_jupyter-0.1.18.tgz
vgrid_jupyter/nbextension/__init__.py
vgrid_jupyter/nbextension/static/extension.js
vgrid_jupyter/nbextension/static/index.css
vgrid_jupyter/nbextension/static/index.css.map
vgrid_jupyter/nbextension/static/index.js
vgrid_jupyter/nbextension/static/index.js.map
vgrid_jupyter/tests/__init__.py
vgrid_jupyter/tests/conftest.py
vgrid_jupyter/tests/test_example.py
vgrid_jupyter/tests/test_nbextension_path.py
vgrid_jupyter-0.1.18.data/data/etc/jupyter/nbconfig/notebook.d/vgrid_jupyter.json
vgrid_jupyter-0.1.18.data/data/share/jupyter/lab/extensions/vgrid_jupyter-0.1.18.tgz
vgrid_jupyter-0.1.18.data/data/share/jupyter/nbextensions/vgrid_jupyter/extension.js
vgrid_jupyter-0.1.18.data/data/share/jupyter/nbextensions/vgrid_jupyter/index.css
vgrid_jupyter-0.1.18.data/data/share/jupyter/nbextensions/vgrid_jupyter/index.css.map
vgrid_jupyter-0.1.18.data/data/share/jupyter/nbextensions/vgrid_jupyter/index.js
vgrid_jupyter-0.1.18.data/data/share/jupyter/nbextensions/vgrid_jupyter/index.js.map
vgrid_jupyter-0.1.18.dist-info/METADATA
vgrid_jupyter-0.1.18.dist-info/WHEEL
vgrid_jupyter-0.1.18.dist-info/top_level.txt
vgrid_jupyter-0.1.18.dist-info/RECORD
